gpucompare/__init__.py
gpucompare/__main__.py
gpucompare/compare.py
gpucompare/parse.py
gpucompare-1.0.0.dist-info/entry_points.txt
gpucompare-1.0.0.dist-info/LICENSE
gpucompare-1.0.0.dist-info/WHEEL
gpucompare-1.0.0.dist-info/METADATA
gpucompare-1.0.0.dist-info/RECORD
