Metadata-Version: 2.1
Name: gpucompare
Version: 1.0.0
Summary: Compare GPUs
Home-page: https://github.com/kHarshit/gpucompare
License: MIT
Author: kHarshit
Author-email: kumar_harshit@outlook.com
Requires-Python: >=3.9,<4.0
Classifier: Development Status :: 1 - Planning
Classifier: Intended Audience :: Developers
Classifier: License :: OSI Approved :: MIT License
Classifier: Operating System :: OS Independent
Classifier: Programming Language :: Python :: 3
Classifier: Programming Language :: Python :: 3.10
Classifier: Programming Language :: Python :: 3.9
Classifier: Topic :: Software Development :: Libraries :: Python Modules
Requires-Dist: rich (>=12.5.1,<13.0.0)
Requires-Dist: typer[all] (>=0.6.1,<0.7.0)
Project-URL: Repository, https://github.com/kHarshit/gpucompare
